mdview/__init__.py
mdview/static/pygments.css
mdview/templates/base.html
mdview-0.1.0.dist-info/LICENSE
mdview-0.1.0.dist-info/METADATA
mdview-0.1.0.dist-info/WHEEL
mdview-0.1.0.dist-info/entry_points.txt
mdview-0.1.0.dist-info/top_level.txt
mdview-0.1.0.dist-info/RECORD
