Metadata-Version: 2.1
Name: mdview
Version: 0.1.0
Summary: Markdown viewer
Home-page: https://github.com/guyru/mdview
Author: Guy Rutenberg
Author-email: guyrutenberg@gmail.com
License: GPLv3+
Platform: UNKNOWN
Classifier: Development Status :: 4 - Beta
Classifier: Environment :: Web Environment
Classifier: Intended Audience :: Developers
Classifier: Intended Audience :: End Users/Desktop
Classifier: License :: OSI Approved :: GNU General Public License (GPL)
Classifier: Operating System :: OS Independent
Classifier: Framework :: Flask
Requires-Dist: Pygments
Requires-Dist: flask
Requires-Dist: markdown
